yampex/__init__.py
yampex/adjust.py
yampex/annotate.py
yampex/helper.py
yampex/options.py
yampex/plot.py
yampex/scaling.py
yampex/subplot.py
yampex/textbox.py
yampex/tools.py
yampex/util.py
yampex/examples/__init__.py
yampex/examples/annotate-simple.py
yampex/examples/annotate.py
yampex/examples/comparison.py
yampex/examples/exponential.py
yampex/examples/legend.py
yampex/examples/logplot.py
yampex/examples/make_png.py
yampex/examples/mosfet_cdg.py
yampex/examples/mosfet_n.py
yampex/examples/mosfet_vdsp.py
yampex/examples/noisy.py
yampex/examples/sincos-one-subplot.py
yampex/examples/sincos.py
yampex/examples/timex.py
yampex/scripts/__init__.py
yampex/scripts/examples.py
yampex/test/__init__.py
yampex/test/test_annotate.py
yampex-1.0.1.dist-info/LICENSE.txt
yampex-1.0.1.dist-info/METADATA
yampex-1.0.1.dist-info/NOTICE
yampex-1.0.1.dist-info/WHEEL
yampex-1.0.1.dist-info/entry_points.txt
yampex-1.0.1.dist-info/top_level.txt
yampex-1.0.1.dist-info/zip-safe
yampex-1.0.1.dist-info/RECORD
