Metadata-Version: 2.1
Name: yampex
Version: 1.0.1
Summary: Yet Another Matplotlib Extension, with simplified subplotting & annotations. 
Home-page: http://edsuom.com/yampex.html
Author: Edwin A. Suominen
Author-email: foss@edsuom.com
Maintainer: Edwin A. Suominen
Maintainer-email: foss@edsuom.com
License: Apache License (2.0)
Project-URL: GitHub, https://github.com/edsuom/yampex
Project-URL: API, http://edsuom.com/yampex/yampex.html
Keywords: matplotlib,numpy,extension,subplots,annotations,plots,plotting
Platform: OS Independent
Classifier: Development Status :: 5 - Production/Stable
Classifier: Intended Audience :: Developers
Classifier: Intended Audience :: Science/Research
Classifier: License :: OSI Approved :: Apache Software License
Classifier: Operating System :: OS Independent
Classifier: Programming Language :: Python :: 2.7
Classifier: Programming Language :: Python :: 3
Classifier: Topic :: Software Development :: Libraries :: Python Modules
Classifier: Topic :: Scientific/Engineering :: Visualization
License-File: LICENSE.txt
License-File: NOTICE
Requires-Dist: numpy
Requires-Dist: matplotlib
Requires-Dist: screeninfo
